{
	"success": true,
	"message": "success response",
	"response": {
		"truck_id": "AM027",
		"data": [{
			"id": 26,
			"site_id": "RTN",
			"hole_code": "A3",
			"deep": "7.0",
			"charge_started_at": "2022-12-14 11:38:29.000",
			"charge_finished_at": "2022-12-14 11:39:54.000",
			"charge_duration": "00:01:25.0000000",
			"an_weight": "0.0",
			"fo_weight": "0.0",
			"plan_weight": "80.640000000000001",
			"actual_weight": "80.840000000000003",
			"stemming_height": "2.8889999999999998",
			"an_leftover": "4428.174",
			"fo_leftover": "698.75",
			"plan_pf": "0.16",
			"actual_pf": "0.16",
			"volume": "0.0",
			"condition": "0",
			"created_at": null,
			"updated_at": null,
			"site_key": null,
			"truck_id": "AM027"
		}, {
			"id": 27,
			"site_id": "RTN",
			"hole_code": "A3",
			"deep": "7.0",
			"charge_started_at": "2022-12-14 11:40:01.000",
			"charge_finished_at": "2022-12-14 11:41:18.000",
			"charge_duration": "00:01:17.0000000",
			"an_weight": "0.0",
			"fo_weight": "0.0",
			"plan_weight": "120.64",
			"actual_weight": "120.84399999999999",
			"stemming_height": "2.8889999999999998",
			"an_leftover": "4126.2150000000001",
			"fo_leftover": "697.56500000000005",
			"plan_pf": "0.16",
			"actual_pf": "0.23999999999999999",
			"volume": "0.0",
			"condition": "0",
			"created_at": null,
			"updated_at": null,
			"site_key": null,
			"truck_id": "AM027"
		}, {
			"id": 28,
			"site_id": "RTN",
			"hole_code": "A3",
			"deep": "7.0",
			"charge_started_at": "2022-12-14 11:44:16.000",
			"charge_finished_at": "2022-12-14 11:44:52.000",
			"charge_duration": "00:00:36.0000000",
			"an_weight": "0.0",
			"fo_weight": "0.0",
			"plan_weight": "80.640000000000001",
			"actual_weight": "29.869",
			"stemming_height": "2.8889999999999998",
			"an_leftover": "4096.549",
			"fo_leftover": "697.43499999999995",
			"plan_pf": "0.16",
			"actual_pf": "5.8999999999999997E-2",
			"volume": "0.0",
			"condition": "0",
			"created_at": null,
			"updated_at": null,
			"site_key": null,
			"truck_id": "AM027"
		}, {
			"id": 29,
			"site_id": "RTN",
			"hole_code": "A5",
			"deep": "7.0",
			"charge_started_at": "2022-12-14 11:46:37.000",
			"charge_finished_at": "2022-12-14 11:49:50.000",
			"charge_duration": "00:03:13.0000000",
			"an_weight": "119.206",
			"fo_weight": "0.53000000000000003",
			"plan_weight": "160.63999999999999",
			"actual_weight": "119.206",
			"stemming_height": "2.8889999999999998",
			"an_leftover": "3821.8800000000001",
			"fo_leftover": "696.505",
			"plan_pf": "0.16",
			"actual_pf": "0.23699999999999999",
			"volume": "0.0",
			"condition": "0",
			"created_at": null,
			"updated_at": null,
			"site_key": null,
			"truck_id": "AM027"
		}, {
			"id": 30,
			"site_id": "RTN",
			"hole_code": "A5",
			"deep": "7.0",
			"charge_started_at": "2022-12-14 11:49:56.000",
			"charge_finished_at": "2022-12-14 11:50:26.000",
			"charge_duration": "00:00:30.0000000",
			"an_weight": "80.852999999999994",
			"fo_weight": "0.35499999999999998",
			"plan_weight": "80.640000000000001",
			"actual_weight": "80.852999999999994",
			"stemming_height": "2.8889999999999998",
			"an_leftover": "3741.2289999999998",
			"fo_leftover": "696.15499999999997",
			"plan_pf": "0.16",
			"actual_pf": "0.16",
			"volume": "0.0",
			"condition": "0",
			"created_at": null,
			"updated_at": null,
			"site_key": null,
			"truck_id": "AM027"
		}, {
			"id": 31,
			"site_id": "RTN",
			"hole_code": "A6",
			"deep": "7.0",
			"charge_started_at": "2022-12-14 11:51:14.000",
			"charge_finished_at": "2022-12-14 11:51:43.000",
			"charge_duration": "00:00:29.0000000",
			"an_weight": "80.846000000000004",
			"fo_weight": "0.34000000000000002",
			"plan_weight": "80.640000000000001",
			"actual_weight": "80.846000000000004",
			"stemming_height": "2.8889999999999998",
			"an_leftover": "3660.5790000000002",
			"fo_leftover": "695.82500000000005",
			"plan_pf": "0.16",
			"actual_pf": "0.16",
			"volume": "0.0",
			"condition": "0",
			"created_at": null,
			"updated_at": null,
			"site_key": null,
			"truck_id": "AM027"
		}, {
			"id": 32,
			"site_id": "RTN",
			"hole_code": "A7",
			"deep": "7.0",
			"charge_started_at": "2022-12-14 11:52:20.000",
			"charge_finished_at": "2022-12-14 11:52:48.000",
			"charge_duration": "00:00:28.0000000",
			"an_weight": "80.878",
			"fo_weight": "0.93999999999999995",
			"plan_weight": "80.640000000000001",
			"actual_weight": "80.878",
			"stemming_height": "2.8889999999999998",
			"an_leftover": "3579.9209999999998",
			"fo_leftover": "694.88999999999999",
			"plan_pf": "0.16",
			"actual_pf": "0.16",
			"volume": "0.0",
			"condition": "0",
			"created_at": null,
			"updated_at": null,
			"site_key": null,
			"truck_id": "AM027"
		}, {
			"id": 33,
			"site_id": "RTN",
			"hole_code": "A8",
			"deep": "7.0",
			"charge_started_at": "2022-12-14 11:53:50.000",
			"charge_finished_at": "2022-12-14 11:53:50.000",
			"charge_duration": "00:00:00.0000000",
			"an_weight": "0.0",
			"fo_weight": "0.0",
			"plan_weight": "80.640000000000001",
			"actual_weight": "0.0",
			"stemming_height": "2.8889999999999998",
			"an_leftover": "3579.9209999999998",
			"fo_leftover": "694.88999999999999",
			"plan_pf": "0.16",
			"actual_pf": "0.0",
			"volume": "0.0",
			"condition": "0",
			"created_at": null,
			"updated_at": null,
			"site_key": null,
			"truck_id": "AM027"
		}, {
			"id": 34,
			"site_id": "RTN",
			"hole_code": "A8",
			"deep": "7.0",
			"charge_started_at": "2022-12-14 11:53:57.000",
			"charge_finished_at": "2022-12-14 11:54:26.000",
			"charge_duration": "00:00:29.0000000",
			"an_weight": "80.852999999999994",
			"fo_weight": "0.92500000000000004",
			"plan_weight": "80.640000000000001",
			"actual_weight": "80.852999999999994",
			"stemming_height": "2.8889999999999998",
			"an_leftover": "3499.2710000000002",
			"fo_leftover": "693.97000000000003",
			"plan_pf": "0.16",
			"actual_pf": "0.16",
			"volume": "0.0",
			"condition": "0",
			"created_at": null,
			"updated_at": null,
			"site_key": null,
			"truck_id": "AM027"
		}, {
			"id": 35,
			"site_id": "RTN",
			"hole_code": "B1",
			"deep": "7.0",
			"charge_started_at": "2022-12-14 11:54:56.000",
			"charge_finished_at": "2022-12-14 11:55:25.000",
			"charge_duration": "00:00:29.0000000",
			"an_weight": "80.835999999999999",
			"fo_weight": "0.92500000000000004",
			"plan_weight": "80.640000000000001",
			"actual_weight": "80.835999999999999",
			"stemming_height": "2.8889999999999998",
			"an_leftover": "3418.6170000000002",
			"fo_leftover": "693.04999999999995",
			"plan_pf": "0.16",
			"actual_pf": "0.16",
			"volume": "0.0",
			"condition": "0",
			"created_at": null,
			"updated_at": null,
			"site_key": null,
			"truck_id": "AM027"
		}, {
			"id": 36,
			"site_id": "RTN",
			"hole_code": "B2",
			"deep": "7.0",
			"charge_started_at": "2022-12-14 11:56:03.000",
			"charge_finished_at": "2022-12-14 11:56:31.000",
			"charge_duration": "00:00:28.0000000",
			"an_weight": "80.870999999999995",
			"fo_weight": "0.93500000000000005",
			"plan_weight": "80.640000000000001",
			"actual_weight": "80.870999999999995",
			"stemming_height": "2.8889999999999998",
			"an_leftover": "3337.9520000000002",
			"fo_leftover": "692.13",
			"plan_pf": "0.16",
			"actual_pf": "0.16",
			"volume": "0.0",
			"condition": "0",
			"created_at": null,
			"updated_at": null,
			"site_key": null,
			"truck_id": "AM027"
		}, {
			"id": 37,
			"site_id": "RTN",
			"hole_code": "B3",
			"deep": "7.0",
			"charge_started_at": "2022-12-14 11:57:06.000",
			"charge_finished_at": "2022-12-14 11:58:11.000",
			"charge_duration": "00:01:04.0000000",
			"an_weight": "77.521000000000001",
			"fo_weight": "0.92500000000000004",
			"plan_weight": "80.640000000000001",
			"actual_weight": "77.521000000000001",
			"stemming_height": "2.8889999999999998",
			"an_leftover": "3260.5990000000002",
			"fo_leftover": "691.21500000000003",
			"plan_pf": "0.16",
			"actual_pf": "0.154",
			"volume": "0.0",
			"condition": "0",
			"created_at": null,
			"updated_at": null,
			"site_key": null,
			"truck_id": "AM027"
		}, {
			"id": 38,
			"site_id": "RTN",
			"hole_code": "B9",
			"deep": "7.0",
			"charge_started_at": "2022-12-14 11:58:45.000",
			"charge_finished_at": "2022-12-14 12:00:44.000",
			"charge_duration": "00:01:59.0000000",
			"an_weight": "70.126000000000005",
			"fo_weight": "0.83999999999999997",
			"plan_weight": "80.640000000000001",
			"actual_weight": "70.126000000000005",
			"stemming_height": "2.8889999999999998",
			"an_leftover": "3189.0340000000001",
			"fo_leftover": "690.36500000000001",
			"plan_pf": "0.16",
			"actual_pf": "0.13900000000000001",
			"volume": "0.0",
			"condition": "0",
			"created_at": null,
			"updated_at": null,
			"site_key": null,
			"truck_id": "AM027"
		}, {
			"id": 39,
			"site_id": "RTN",
			"hole_code": "B10",
			"deep": "7.0",
			"charge_started_at": "2022-12-14 12:00:51.000",
			"charge_finished_at": "2022-12-14 12:01:44.000",
			"charge_duration": "00:00:53.0000000",
			"an_weight": "78.340000000000003",
			"fo_weight": "0.92000000000000004",
			"plan_weight": "80.640000000000001",
			"actual_weight": "78.340000000000003",
			"stemming_height": "2.8889999999999998",
			"an_leftover": "3110.8620000000001",
			"fo_leftover": "689.45000000000005",
			"plan_pf": "0.16",
			"actual_pf": "0.155",
			"volume": "0.0",
			"condition": "0",
			"created_at": null,
			"updated_at": null,
			"site_key": null,
			"truck_id": "AM027"
		}, {
			"id": 40,
			"site_id": "RTN",
			"hole_code": "B11",
			"deep": "7.0",
			"charge_started_at": "2022-12-14 12:01:50.000",
			"charge_finished_at": "2022-12-14 12:02:36.000",
			"charge_duration": "00:00:46.0000000",
			"an_weight": "72.037000000000006",
			"fo_weight": "0.88",
			"plan_weight": "80.640000000000001",
			"actual_weight": "72.037000000000006",
			"stemming_height": "2.8889999999999998",
			"an_leftover": "3039.0239999999999",
			"fo_leftover": "688.57500000000005",
			"plan_pf": "0.16",
			"actual_pf": "0.14299999999999999",
			"volume": "0.0",
			"condition": "0",
			"created_at": null,
			"updated_at": null,
			"site_key": null,
			"truck_id": "AM027"
		}, {
			"id": 41,
			"site_id": "RTN",
			"hole_code": "B12",
			"deep": "7.0",
			"charge_started_at": "2022-12-14 12:02:43.000",
			"charge_finished_at": "2022-12-14 12:03:32.000",
			"charge_duration": "00:00:49.0000000",
			"an_weight": "66.896000000000001",
			"fo_weight": "0.81499999999999995",
			"plan_weight": "80.640000000000001",
			"actual_weight": "66.896000000000001",
			"stemming_height": "2.8889999999999998",
			"an_leftover": "2972.328",
			"fo_leftover": "687.76499999999999",
			"plan_pf": "0.16",
			"actual_pf": "0.13300000000000001",
			"volume": "0.0",
			"condition": "0",
			"created_at": null,
			"updated_at": null,
			"site_key": null,
			"truck_id": "AM027"
		}, {
			"id": 42,
			"site_id": "RTN",
			"hole_code": "B12",
			"deep": "7.0",
			"charge_started_at": "2022-12-14 12:03:37.000",
			"charge_finished_at": "2022-12-14 12:04:56.000",
			"charge_duration": "00:01:19.0000000",
			"an_weight": "48.167000000000002",
			"fo_weight": "0.45500000000000002",
			"plan_weight": "80.640000000000001",
			"actual_weight": "48.167000000000002",
			"stemming_height": "2.8889999999999998",
			"an_leftover": "2924.259",
			"fo_leftover": "687.30999999999995",
			"plan_pf": "0.16",
			"actual_pf": "9.6000000000000002E-2",
			"volume": "0.0",
			"condition": "0",
			"created_at": null,
			"updated_at": null,
			"site_key": null,
			"truck_id": "AM027"
		}, {
			"id": 43,
			"site_id": "RTN",
			"hole_code": "B13",
			"deep": "7.0",
			"charge_started_at": "2022-12-14 12:05:03.000",
			"charge_finished_at": "2022-12-14 12:05:44.000",
			"charge_duration": "00:00:41.0000000",
			"an_weight": "61.817",
			"fo_weight": "0.26500000000000001",
			"plan_weight": "80.640000000000001",
			"actual_weight": "61.817",
			"stemming_height": "2.8889999999999998",
			"an_leftover": "2862.4459999999999",
			"fo_leftover": "687.04499999999996",
			"plan_pf": "0.16",
			"actual_pf": "0.123",
			"volume": "0.0",
			"condition": "0",
			"created_at": null,
			"updated_at": null,
			"site_key": null,
			"truck_id": "AM027"
		}, {
			"id": 44,
			"site_id": "RTN",
			"hole_code": "B14",
			"deep": "7.0",
			"charge_started_at": "2022-12-14 12:05:54.000",
			"charge_finished_at": "2022-12-14 12:06:38.000",
			"charge_duration": "00:00:44.0000000",
			"an_weight": "68.506",
			"fo_weight": "0.26000000000000001",
			"plan_weight": "80.640000000000001",
			"actual_weight": "68.506",
			"stemming_height": "2.8889999999999998",
			"an_leftover": "2794.136",
			"fo_leftover": "686.78499999999997",
			"plan_pf": "0.16",
			"actual_pf": "0.13600000000000001",
			"volume": "0.0",
			"condition": "0",
			"created_at": null,
			"updated_at": null,
			"site_key": null,
			"truck_id": "AM027"
		}, {
			"id": 45,
			"site_id": "RTN",
			"hole_code": "B15",
			"deep": "7.0",
			"charge_started_at": "2022-12-14 12:06:44.000",
			"charge_finished_at": "2022-12-14 12:07:34.000",
			"charge_duration": "00:00:50.0000000",
			"an_weight": "76.244",
			"fo_weight": "0.28000000000000003",
			"plan_weight": "80.640000000000001",
			"actual_weight": "76.244",
			"stemming_height": "2.8889999999999998",
			"an_leftover": "2717.9969999999998",
			"fo_leftover": "686.505",
			"plan_pf": "0.16",
			"actual_pf": "0.151",
			"volume": "0.0",
			"condition": "0",
			"created_at": null,
			"updated_at": null,
			"site_key": null,
			"truck_id": "AM027"
		}, {
			"id": 46,
			"site_id": "RTSG",
			"hole_code": "A1",
			"deep": "7.0",
			"charge_started_at": "2022-12-14 14:51:36.000",
			"charge_finished_at": "2022-12-14 14:51:36.000",
			"charge_duration": "00:00:00.0000000",
			"an_weight": "0.0",
			"fo_weight": "0.0",
			"plan_weight": "80.640000000000001",
			"actual_weight": "0.0",
			"stemming_height": "2.8889999999999998",
			"an_leftover": "5000.0",
			"fo_leftover": "700.0",
			"plan_pf": "0.16",
			"actual_pf": "0.0",
			"volume": "0.0",
			"condition": "0",
			"created_at": null,
			"updated_at": null,
			"site_key": null,
			"truck_id": "AM027"
		}, {
			"id": 47,
			"site_id": "RTSG",
			"hole_code": "A1",
			"deep": "7.0",
			"charge_started_at": "2022-12-14 14:55:45.000",
			"charge_finished_at": "2022-12-14 14:55:45.000",
			"charge_duration": "00:00:00.0000000",
			"an_weight": "0.0",
			"fo_weight": "0.0",
			"plan_weight": "80.640000000000001",
			"actual_weight": "0.0",
			"stemming_height": "2.8889999999999998",
			"an_leftover": "5000.0",
			"fo_leftover": "700.0",
			"plan_pf": "0.16",
			"actual_pf": "0.0",
			"volume": "0.0",
			"condition": "0",
			"created_at": null,
			"updated_at": null,
			"site_key": null,
			"truck_id": "AM027"
		}, {
			"id": 1046,
			"site_id": "RTSG",
			"hole_code": "00",
			"deep": "7.0",
			"charge_started_at": "2022-12-17 10:22:44.000",
			"charge_finished_at": "2022-12-17 10:23:44.000",
			"charge_duration": "00:01:00.0000000",
			"an_weight": "91.293999999999997",
			"fo_weight": "0.35499999999999998",
			"plan_weight": "91.034999999999997",
			"actual_weight": "91.293999999999997",
			"stemming_height": "2.359",
			"an_leftover": "4908.9549999999999",
			"fo_leftover": "699.64499999999998",
			"plan_pf": "0.17000000000000001",
			"actual_pf": "0.17000000000000001",
			"volume": "0.0",
			"condition": "0",
			"created_at": null,
			"updated_at": null,
			"site_key": null,
			"truck_id": "AM027"
		}, {
			"id": 1047,
			"site_id": "RTSG",
			"hole_code": "H8",
			"deep": "7.0",
			"charge_started_at": "2022-12-17 10:23:52.000",
			"charge_finished_at": "2022-12-17 10:24:39.000",
			"charge_duration": "00:00:47.0000000",
			"an_weight": "63.912999999999997",
			"fo_weight": "0.29499999999999998",
			"plan_weight": "91.034999999999997",
			"actual_weight": "63.912999999999997",
			"stemming_height": "2.359",
			"an_leftover": "4845.2830000000004",
			"fo_leftover": "699.35000000000002",
			"plan_pf": "0.17000000000000001",
			"actual_pf": "0.11899999999999999",
			"volume": "0.0",
			"condition": "0",
			"created_at": null,
			"updated_at": null,
			"site_key": null,
			"truck_id": "AM027"
		}, {
			"id": 1048,
			"site_id": "RTSG",
			"hole_code": "H2",
			"deep": "7.0",
			"charge_started_at": "2022-12-17 10:24:46.000",
			"charge_finished_at": "2022-12-17 10:25:41.000",
			"charge_duration": "00:00:55.0000000",
			"an_weight": "85.274000000000001",
			"fo_weight": "0.41999999999999998",
			"plan_weight": "91.034999999999997",
			"actual_weight": "85.274000000000001",
			"stemming_height": "2.359",
			"an_leftover": "4760.2359999999999",
			"fo_leftover": "698.92999999999995",
			"plan_pf": "0.17000000000000001",
			"actual_pf": "0.159",
			"volume": "0.0",
			"condition": "0",
			"created_at": null,
			"updated_at": null,
			"site_key": null,
			"truck_id": "AM027"
		}, {
			"id": 1049,
			"site_id": "RTSG",
			"hole_code": "G2",
			"deep": "7.0",
			"charge_started_at": "2022-12-17 10:25:48.000",
			"charge_finished_at": "2022-12-17 10:26:40.000",
			"charge_duration": "00:00:52.0000000",
			"an_weight": "81.679000000000002",
			"fo_weight": "0.40999999999999998",
			"plan_weight": "91.034999999999997",
			"actual_weight": "81.679000000000002",
			"stemming_height": "2.359",
			"an_leftover": "4678.71",
			"fo_leftover": "698.52499999999998",
			"plan_pf": "0.17000000000000001",
			"actual_pf": "0.153",
			"volume": "0.0",
			"condition": "0",
			"created_at": null,
			"updated_at": null,
			"site_key": null,
			"truck_id": "AM027"
		}, {
			"id": 1050,
			"site_id": "RTSG",
			"hole_code": "H3",
			"deep": "7.0",
			"charge_started_at": "2022-12-17 10:26:44.000",
			"charge_finished_at": "2022-12-17 10:27:16.000",
			"charge_duration": "00:00:32.0000000",
			"an_weight": "91.174999999999997",
			"fo_weight": "0.45000000000000001",
			"plan_weight": "91.034999999999997",
			"actual_weight": "91.174999999999997",
			"stemming_height": "2.359",
			"an_leftover": "4587.665",
			"fo_leftover": "698.07500000000005",
			"plan_pf": "0.17000000000000001",
			"actual_pf": "0.17000000000000001",
			"volume": "0.0",
			"condition": "0",
			"created_at": null,
			"updated_at": null,
			"site_key": null,
			"truck_id": "AM027"
		}, {
			"id": 1051,
			"site_id": "RTSG",
			"hole_code": "H4",
			"deep": "7.0",
			"charge_started_at": "2022-12-17 10:27:41.000",
			"charge_finished_at": "2022-12-17 10:28:16.000",
			"charge_duration": "00:00:35.0000000",
			"an_weight": "91.168000000000006",
			"fo_weight": "0.505",
			"plan_weight": "91.034999999999997",
			"actual_weight": "91.168000000000006",
			"stemming_height": "2.359",
			"an_leftover": "4496.6199999999999",
			"fo_leftover": "697.57500000000005",
			"plan_pf": "0.17000000000000001",
			"actual_pf": "0.17000000000000001",
			"volume": "0.0",
			"condition": "0",
			"created_at": null,
			"updated_at": null,
			"site_key": null,
			"truck_id": "AM027"
		}, {
			"id": 1052,
			"site_id": "RTSG",
			"hole_code": "H5",
			"deep": "7.0",
			"charge_started_at": "2022-12-17 10:28:42.000",
			"charge_finished_at": "2022-12-17 10:29:14.000",
			"charge_duration": "00:00:32.0000000",
			"an_weight": "91.182000000000002",
			"fo_weight": "0.55500000000000005",
			"plan_weight": "91.034999999999997",
			"actual_weight": "91.182000000000002",
			"stemming_height": "2.359",
			"an_leftover": "4405.5780000000004",
			"fo_leftover": "697.01999999999998",
			"plan_pf": "0.17000000000000001",
			"actual_pf": "0.17000000000000001",
			"volume": "0.0",
			"condition": "0",
			"created_at": null,
			"updated_at": null,
			"site_key": null,
			"truck_id": "AM027"
		}, {
			"id": 1053,
			"site_id": "RTSG",
			"hole_code": "H6",
			"deep": "7.0",
			"charge_started_at": "2022-12-17 10:29:42.000",
			"charge_finished_at": "2022-12-17 10:30:14.000",
			"charge_duration": "00:00:32.0000000",
			"an_weight": "91.140000000000001",
			"fo_weight": "0.48999999999999999",
			"plan_weight": "91.034999999999997",
			"actual_weight": "91.140000000000001",
			"stemming_height": "2.359",
			"an_leftover": "4314.5360000000001",
			"fo_leftover": "696.52999999999997",
			"plan_pf": "0.17000000000000001",
			"actual_pf": "0.17000000000000001",
			"volume": "0.0",
			"condition": "0",
			"created_at": null,
			"updated_at": null,
			"site_key": null,
			"truck_id": "AM027"
		}, {
			"id": 1054,
			"site_id": "RTSG",
			"hole_code": "G1",
			"deep": "7.0",
			"charge_started_at": "2022-12-17 10:31:36.000",
			"charge_finished_at": "2022-12-17 10:32:06.000",
			"charge_duration": "00:00:30.0000000",
			"an_weight": "91.233999999999995",
			"fo_weight": "0.52000000000000002",
			"plan_weight": "91.034999999999997",
			"actual_weight": "91.233999999999995",
			"stemming_height": "2.359",
			"an_leftover": "4223.4899999999998",
			"fo_leftover": "696.00999999999999",
			"plan_pf": "0.17000000000000001",
			"actual_pf": "0.17000000000000001",
			"volume": "0.0",
			"condition": "0",
			"created_at": null,
			"updated_at": null,
			"site_key": null,
			"truck_id": "AM027"
		}, {
			"id": 1055,
			"site_id": "RTSG",
			"hole_code": "G3",
			"deep": "7.0",
			"charge_started_at": "2022-12-17 10:34:10.000",
			"charge_finished_at": "2022-12-17 10:35:07.000",
			"charge_duration": "00:00:57.0000000",
			"an_weight": "91.238",
			"fo_weight": "0.56000000000000005",
			"plan_weight": "91.034999999999997",
			"actual_weight": "91.238",
			"stemming_height": "2.359",
			"an_leftover": "4057.3519999999999",
			"fo_leftover": "694.98000000000002",
			"plan_pf": "0.17000000000000001",
			"actual_pf": "0.17000000000000001",
			"volume": "0.0",
			"condition": "0",
			"created_at": null,
			"updated_at": null,
			"site_key": null,
			"truck_id": "AM027"
		}, {
			"id": 1056,
			"site_id": "RTSG",
			"hole_code": "G4",
			"deep": "7.0",
			"charge_started_at": "2022-12-17 10:35:16.000",
			"charge_finished_at": "2022-12-17 10:35:49.000",
			"charge_duration": "00:00:33.0000000",
			"an_weight": "91.161000000000001",
			"fo_weight": "0.54500000000000004",
			"plan_weight": "91.034999999999997",
			"actual_weight": "91.161000000000001",
			"stemming_height": "2.359",
			"an_leftover": "3966.3099999999999",
			"fo_leftover": "694.44000000000005",
			"plan_pf": "0.17000000000000001",
			"actual_pf": "0.17000000000000001",
			"volume": "0.0",
			"condition": "0",
			"created_at": null,
			"updated_at": null,
			"site_key": null,
			"truck_id": "AM027"
		}, {
			"id": 1057,
			"site_id": "RTSG",
			"hole_code": "G5",
			"deep": "7.0",
			"charge_started_at": "2022-12-17 10:36:18.000",
			"charge_finished_at": "2022-12-17 10:36:48.000",
			"charge_duration": "00:00:30.0000000",
			"an_weight": "91.275999999999996",
			"fo_weight": "0.53500000000000003",
			"plan_weight": "91.034999999999997",
			"actual_weight": "91.275999999999996",
			"stemming_height": "2.359",
			"an_leftover": "3875.2579999999998",
			"fo_leftover": "693.90499999999997",
			"plan_pf": "0.17000000000000001",
			"actual_pf": "0.17000000000000001",
			"volume": "0.0",
			"condition": "0",
			"created_at": null,
			"updated_at": null,
			"site_key": null,
			"truck_id": "AM027"
		}, {
			"id": 1058,
			"site_id": "RTSG",
			"hole_code": "G6",
			"deep": "7.0",
			"charge_started_at": "2022-12-17 10:37:17.000",
			"charge_finished_at": "2022-12-17 10:37:47.000",
			"charge_duration": "00:00:30.0000000",
			"an_weight": "91.290000000000006",
			"fo_weight": "0.53000000000000003",
			"plan_weight": "91.034999999999997",
			"actual_weight": "91.290000000000006",
			"stemming_height": "2.359",
			"an_leftover": "3784.2080000000001",
			"fo_leftover": "693.375",
			"plan_pf": "0.17000000000000001",
			"actual_pf": "0.17000000000000001",
			"volume": "0.0",
			"condition": "0",
			"created_at": null,
			"updated_at": null,
			"site_key": null,
			"truck_id": "AM027"
		}, {
			"id": 1059,
			"site_id": "RTSG",
			"hole_code": "G6",
			"deep": "7.0",
			"charge_started_at": "2022-12-17 10:38:19.000",
			"charge_finished_at": "2022-12-17 10:39:19.000",
			"charge_duration": "00:00:59.0000000",
			"an_weight": "23.187999999999999",
			"fo_weight": "0.14499999999999999",
			"plan_weight": "91.034999999999997",
			"actual_weight": "23.187999999999999",
			"stemming_height": "2.359",
			"an_leftover": "3761.2660000000001",
			"fo_leftover": "693.23000000000002",
			"plan_pf": "0.17000000000000001",
			"actual_pf": "4.2999999999999997E-2",
			"volume": "0.0",
			"condition": "0",
			"created_at": null,
			"updated_at": null,
			"site_key": null,
			"truck_id": "AM027"
		}, {
			"id": 1060,
			"site_id": "RTSG",
			"hole_code": "F1",
			"deep": "7.0",
			"charge_started_at": "2022-12-17 10:39:24.000",
			"charge_finished_at": "2022-12-17 10:39:54.000",
			"charge_duration": "00:00:30.0000000",
			"an_weight": "91.287000000000006",
			"fo_weight": "0.46000000000000002",
			"plan_weight": "91.034999999999997",
			"actual_weight": "91.287000000000006",
			"stemming_height": "2.359",
			"an_leftover": "3670.2170000000001",
			"fo_leftover": "692.77499999999998",
			"plan_pf": "0.17000000000000001",
			"actual_pf": "0.17000000000000001",
			"volume": "0.0",
			"condition": "0",
			"created_at": null,
			"updated_at": null,
			"site_key": null,
			"truck_id": "AM027"
		}, {
			"id": 1061,
			"site_id": "RTSG",
			"hole_code": "F1",
			"deep": "7.0",
			"charge_started_at": "2022-12-17 10:40:09.000",
			"charge_finished_at": "2022-12-17 10:40:40.000",
			"charge_duration": "00:00:31.0000000",
			"an_weight": "91.305000000000007",
			"fo_weight": "0.435",
			"plan_weight": "91.034999999999997",
			"actual_weight": "91.305000000000007",
			"stemming_height": "2.359",
			"an_leftover": "3579.1610000000001",
			"fo_leftover": "692.34500000000003",
			"plan_pf": "0.17000000000000001",
			"actual_pf": "0.17100000000000001",
			"volume": "0.0",
			"condition": "0",
			"created_at": null,
			"updated_at": null,
			"site_key": null,
			"truck_id": "AM027"
		}, {
			"id": 1062,
			"site_id": "RTSG",
			"hole_code": "F3",
			"deep": "7.0",
			"charge_started_at": "2022-12-17 10:41:09.000",
			"charge_finished_at": "2022-12-17 10:41:39.000",
			"charge_duration": "00:00:30.0000000",
			"an_weight": "91.311999999999998",
			"fo_weight": "0.40000000000000002",
			"plan_weight": "91.034999999999997",
			"actual_weight": "91.311999999999998",
			"stemming_height": "2.359",
			"an_leftover": "3488.105",
			"fo_leftover": "691.94500000000005",
			"plan_pf": "0.17000000000000001",
			"actual_pf": "0.17100000000000001",
			"volume": "0.0",
			"condition": "0",
			"created_at": null,
			"updated_at": null,
			"site_key": null,
			"truck_id": "AM027"
		}]
	}
}